Artificial_Neural_Network_Classifier/__init__.py
Artificial_Neural_Network_Classifier/lineardiscriminantanalysis.py
Artificial_Neural_Network_Classifier/linearregression.py
Artificial_Neural_Network_Classifier/logisticregession.py
Artificial_Neural_Network_Classifier/softmaxregression.py
Artificial_Neural_Network_Classifier/tanhiperboliqueregression.py
Artificial_Neural_Network_Classifier/tanhiperboliqueregression_dec.py
Artificial_Neural_Network_Classifier/tanhiperboliqueregression_mixt.py
tests/test.py
Artificial_Neural_Network_Classifier-1.0.22.dist-info/LICENSE
Artificial_Neural_Network_Classifier-1.0.22.dist-info/METADATA
Artificial_Neural_Network_Classifier-1.0.22.dist-info/WHEEL
Artificial_Neural_Network_Classifier-1.0.22.dist-info/top_level.txt
Artificial_Neural_Network_Classifier-1.0.22.dist-info/RECORD
