Metadata-Version: 2.1
Name: Artificial-Neural-Network-Classifier
Version: 1.0.22
Summary: Artificial Neural Network, is a deep learning API written in Python.
Author-email: Ouedraogo Somkieta Rahim Alex <s.r.a.ouedraogo@gmail.com>
Project-URL: Homepage, https://github.com/somkietacode/Artificial_Neural_Network
Project-URL: Bug Tracker, https://github.com/somkietacode/Artificial_Neural_Network/issues
Classifier: Programming Language :: Python :: 3
Classifier: License :: OSI Approved :: MIT License
Classifier: Operating System :: OS Independent
Requires-Python: >=3.7
License-File: LICENSE
Requires-Dist: numpy
Requires-Dist: importlib-metadata ; python_version < "3.7"
